roleml/__init__.py
roleml/essentials.py
roleml/core/__init__.py
roleml/core/context.py
roleml/core/status.py
roleml/core/actor/__init__.py
roleml/core/actor/base.py
roleml/core/actor/helpers.py
roleml/core/actor/status.py
roleml/core/actor/default/__init__.py
roleml/core/actor/default/bootstrap.py
roleml/core/actor/default/impl.py
roleml/core/actor/default/native.py
roleml/core/actor/default/managers/__init__.py
roleml/core/actor/default/managers/channels.py
roleml/core/actor/default/managers/element.py
roleml/core/actor/default/managers/event.py
roleml/core/actor/default/managers/runnable.py
roleml/core/actor/default/managers/service.py
roleml/core/actor/default/managers/task.py
roleml/core/actor/group/__init__.py
roleml/core/actor/group/base.py
roleml/core/actor/group/helpers.py
roleml/core/actor/group/makers.py
roleml/core/actor/group/impl/__init__.py
roleml/core/actor/group/impl/helpers.py
roleml/core/actor/group/impl/null.py
roleml/core/actor/group/impl/sequential.py
roleml/core/actor/group/impl/threaded.py
roleml/core/actor/group/util/__init__.py
roleml/core/actor/group/util/collections.py
roleml/core/actor/manager/__init__.py
roleml/core/actor/manager/bases.py
roleml/core/actor/manager/helpers.py
roleml/core/builders/__init__.py
roleml/core/builders/actor.py
roleml/core/builders/element.py
roleml/core/builders/helpers.py
roleml/core/builders/role.py
roleml/core/messaging/__init__.py
roleml/core/messaging/base.py
roleml/core/messaging/exceptions.py
roleml/core/messaging/null.py
roleml/core/messaging/types.py
roleml/core/role/__init__.py
roleml/core/role/base.py
roleml/core/role/channels.py
roleml/core/role/elements.py
roleml/core/role/exceptions.py
roleml/core/role/helpers.py
roleml/core/role/naming.py
roleml/core/role/types.py
roleml/extensions/__init__.py
roleml/extensions/containerization/__init__.py
roleml/extensions/containerization/builders/actor.py
roleml/extensions/containerization/builders/role.py
roleml/extensions/containerization/builders/spec.py
roleml_ai-0.3.0.dist-info/LICENSE
roleml_ai-0.3.0.dist-info/METADATA
roleml_ai-0.3.0.dist-info/WHEEL
roleml_ai-0.3.0.dist-info/top_level.txt
roleml_ai-0.3.0.dist-info/RECORD
