Metadata-Version: 2.1
Name: roleml-ai
Version: 0.3.0
Summary: A role-oriented programming model for distributed ML
Classifier: Development Status :: 3 - Alpha
Classifier: Intended Audience :: Developers
Classifier: Intended Audience :: Science/Research
Classifier: Topic :: System :: Distributed Computing
Classifier: Topic :: Scientific/Engineering :: Artificial Intelligence
Requires-Python: <4,>=3.9
License-File: LICENSE
Requires-Dist: schema
Requires-Dist: fasteners>=0.19
Requires-Dist: PyYAML
Requires-Dist: typing_extensions>=4.4.0
Provides-Extra: http
Requires-Dist: flask; extra == "http"
Requires-Dist: werkzeug; extra == "http"
Requires-Dist: charset-normalizer>=3; extra == "http"
Requires-Dist: requests; extra == "http"
Provides-Extra: grpc
Requires-Dist: grpcio; extra == "grpc"
Requires-Dist: grpcio-tools; extra == "grpc"
Provides-Extra: containerization
Requires-Dist: psutil; extra == "containerization"
Requires-Dist: docker; extra == "containerization"
Requires-Dist: podman; extra == "containerization"
Requires-Dist: sqlalchemy; extra == "containerization"
Provides-Extra: profiling
Requires-Dist: viztracer; extra == "profiling"
Provides-Extra: starter
Requires-Dist: grpcio; extra == "starter"
Requires-Dist: grpcio-tools; extra == "starter"
Requires-Dist: viztracer; extra == "starter"
